recipemd/__init__.py
recipemd/data.py
recipemd/filter.py
recipemd/_vendor/__init__.py
recipemd/_vendor/commonmark_extensions/__init__.py
recipemd/_vendor/commonmark_extensions/make_reference_output.py
recipemd/_vendor/commonmark_extensions/plaintext.py
recipemd/_vendor/commonmark_extensions/tables.py
recipemd/_vendor/commonmark_extensions/tests.py
recipemd/cli/__init__.py
recipemd/cli/find.py
recipemd/cli/main.py
tests/__init__.py
tests/test_data.py
tests/test_filter.py
tests/cli/__init__.py
tests/cli/test_main.py
recipemd-4.1.0.dist-info/LICENSE
recipemd-4.1.0.dist-info/LICENSE.GPL
recipemd-4.1.0.dist-info/METADATA
recipemd-4.1.0.dist-info/WHEEL
recipemd-4.1.0.dist-info/entry_points.txt
recipemd-4.1.0.dist-info/top_level.txt
recipemd-4.1.0.dist-info/RECORD
