Metadata-Version: 2.1
Name: recipemd
Version: 4.1.0
Summary: Markdown recipe manager, reference implementation of RecipeMD
Home-page: https://recipemd.org
Author: Tilman Stehr
Author-email: tilman@tilman.ninja
License: UNKNOWN
Project-URL: Documentation, https://recipemd.org/reference_implementation.html
Project-URL: Source, https://github.com/tstehr/recipemd
Platform: UNKNOWN
Classifier: Development Status :: 5 - Production/Stable
Classifier: Environment :: Console
Classifier: Intended Audience :: End Users/Desktop
Classifier: Intended Audience :: Developers
Classifier: Programming Language :: Python :: 3
Classifier: Topic :: Utilities
Classifier: Topic :: Text Processing :: Markup
Classifier: Operating System :: OS Independent
Classifier: License :: OSI Approved :: GNU Lesser General Public License v3 or later (LGPLv3+)
Requires-Python: >=3.7,<4
License-File: LICENSE
License-File: LICENSE.GPL
Requires-Dist: dataclasses-json (<0.6.0,>=0.5.2)
Requires-Dist: yarl (<2.0.0,>=1.3.0)
Requires-Dist: argcomplete (<2.0.0,>=1.10.0)
Requires-Dist: pyparsing (~=2.4.2)
Requires-Dist: markdown-it-py (<3.0.0,>=2.1.0)
Requires-Dist: typing-extensions (<5.0.0,>=4.3.0)
Provides-Extra: dev
Requires-Dist: pytest (==6.2.5) ; extra == 'dev'
Requires-Dist: pytest-cov (==2.8.1) ; extra == 'dev'
Requires-Dist: tox (==3.20.1) ; extra == 'dev'
Requires-Dist: Sphinx (==5.1.1) ; extra == 'dev'
Requires-Dist: m2r2 (==0.3.3) ; extra == 'dev'
Requires-Dist: sphinxcontrib.fulltoc (==1.2.0) ; extra == 'dev'
Requires-Dist: sphinxcontrib.autoprogram (==0.1.7) ; extra == 'dev'
Requires-Dist: sphinx-autodoc-typehints (==1.19.2) ; extra == 'dev'
Requires-Dist: sphinxcontrib.apidoc (==0.3.0) ; extra == 'dev'
Requires-Dist: sphinx-autobuild (==2021.3.14) ; extra == 'dev'
Requires-Dist: twine (==3.1.1) ; extra == 'dev'
Requires-Dist: wheel ; extra == 'dev'
Provides-Extra: docs
Requires-Dist: Sphinx (==5.1.1) ; extra == 'docs'
Requires-Dist: m2r2 (==0.3.3) ; extra == 'docs'
Requires-Dist: sphinxcontrib.fulltoc (==1.2.0) ; extra == 'docs'
Requires-Dist: sphinxcontrib.autoprogram (==0.1.7) ; extra == 'docs'
Requires-Dist: sphinx-autodoc-typehints (==1.19.2) ; extra == 'docs'
Requires-Dist: sphinxcontrib.apidoc (==0.3.0) ; extra == 'docs'
Requires-Dist: sphinx-autobuild (==2021.3.14) ; extra == 'docs'
Provides-Extra: release
Requires-Dist: twine (==3.1.1) ; extra == 'release'
Requires-Dist: wheel ; extra == 'release'
Provides-Extra: tests
Requires-Dist: pytest (==6.2.5) ; extra == 'tests'
Requires-Dist: pytest-cov (==2.8.1) ; extra == 'tests'
Requires-Dist: tox (==3.20.1) ; extra == 'tests'
